svc_infra/__init__.py
svc_infra/apf_payments/README.md
svc_infra/apf_payments/__init__.py
svc_infra/apf_payments/alembic.py
svc_infra/apf_payments/models.py
svc_infra/apf_payments/provider/__init__.py
svc_infra/apf_payments/provider/aiydan.py
svc_infra/apf_payments/provider/base.py
svc_infra/apf_payments/provider/registry.py
svc_infra/apf_payments/provider/stripe.py
svc_infra/apf_payments/schemas.py
svc_infra/apf_payments/service.py
svc_infra/apf_payments/settings.py
svc_infra/api/__init__.py
svc_infra/api/fastapi/__init__.py
svc_infra/api/fastapi/admin/__init__.py
svc_infra/api/fastapi/admin/add.py
svc_infra/api/fastapi/apf_payments/__init__.py
svc_infra/api/fastapi/apf_payments/router.py
svc_infra/api/fastapi/apf_payments/setup.py
svc_infra/api/fastapi/auth/__init__.py
svc_infra/api/fastapi/auth/_cookies.py
svc_infra/api/fastapi/auth/add.py
svc_infra/api/fastapi/auth/gaurd.py
svc_infra/api/fastapi/auth/mfa/__init__.py
svc_infra/api/fastapi/auth/mfa/models.py
svc_infra/api/fastapi/auth/mfa/pre_auth.py
svc_infra/api/fastapi/auth/mfa/router.py
svc_infra/api/fastapi/auth/mfa/security.py
svc_infra/api/fastapi/auth/mfa/utils.py
svc_infra/api/fastapi/auth/mfa/verify.py
svc_infra/api/fastapi/auth/policy.py
svc_infra/api/fastapi/auth/providers.py
svc_infra/api/fastapi/auth/routers/__init__.py
svc_infra/api/fastapi/auth/routers/account.py
svc_infra/api/fastapi/auth/routers/apikey_router.py
svc_infra/api/fastapi/auth/routers/oauth_router.py
svc_infra/api/fastapi/auth/routers/session_router.py
svc_infra/api/fastapi/auth/security.py
svc_infra/api/fastapi/auth/sender.py
svc_infra/api/fastapi/auth/settings.py
svc_infra/api/fastapi/auth/state.py
svc_infra/api/fastapi/auth/ws_security.py
svc_infra/api/fastapi/billing/router.py
svc_infra/api/fastapi/billing/setup.py
svc_infra/api/fastapi/cache/__init__.py
svc_infra/api/fastapi/cache/add.py
svc_infra/api/fastapi/db/__init__.py
svc_infra/api/fastapi/db/http.py
svc_infra/api/fastapi/db/nosql/__init__.py
svc_infra-1.11.0.dist-info/LICENSE
svc_infra-1.11.0.dist-info/METADATA
svc_infra-1.11.0.dist-info/WHEEL
svc_infra-1.11.0.dist-info/entry_points.txt
svc_infra-1.11.0.dist-info/RECORD
