Metadata-Version: 2.3
Name: svc-infra
Version: 1.11.0
Summary: Infrastructure for building and deploying prod-ready services
License: MIT
Keywords: fastapi,sqlalchemy,alembic,auth,infra,async,pydantic
Author: Ali Khatami
Author-email: aliikhatami94@gmail.com
Requires-Python: >=3.11,<4.0
Classifier: Development Status :: 5 - Production/Stable
Classifier: Framework :: FastAPI
Classifier: Intended Audience :: Developers
Classifier: License :: OSI Approved :: MIT License
Classifier: Programming Language :: Python :: 3
Classifier: Programming Language :: Python :: 3.11
Classifier: Programming Language :: Python :: 3.12
Classifier: Programming Language :: Python :: 3.13
Classifier: Programming Language :: Python :: 3 :: Only
Classifier: Topic :: Internet :: WWW/HTTP :: HTTP Servers
Classifier: Topic :: Software Development :: Libraries :: Python Modules
Classifier: Typing :: Typed
Provides-Extra: adyen
Provides-Extra: duckdb
Provides-Extra: metrics
Provides-Extra: mongodb
Provides-Extra: mssql
Provides-Extra: mysql
Provides-Extra: payments
Provides-Extra: pg
Provides-Extra: pg2
Provides-Extra: redshift
Provides-Extra: s3
Provides-Extra: snowflake
Provides-Extra: sqlite
Provides-Extra: stripe
Requires-Dist: adyen (>=10.0.0) ; extra == "payments" or extra == "adyen"
Requires-Dist: aioboto3 (>=12.0.0) ; extra == "s3"
Requires-Dist: aiofiles (>=24.0.0)
Requires-Dist: aiosqlite (>=0.19.0) ; extra == "sqlite"
Requires-Dist: alembic (>=1.13.0)
Requires-Dist: asyncpg (>=0.29.0) ; extra == "pg"
Requires-Dist: authlib (>=1.0.0)
Requires-Dist: cashews[redis] (>=7.0)
Requires-Dist: duckdb (>=0.10.0) ; extra == "duckdb"
Requires-Dist: email-validator (>=2.0.0)
Requires-Dist: fastapi (>=0.110.0)
Requires-Dist: fastapi-users-db-sqlalchemy (>=7.0.0)
Requires-Dist: fastapi-users[oauth] (>=14.0.0)
Requires-Dist: greenlet (>=3.0)
Requires-Dist: httpx (>=0.25.0)
Requires-Dist: httpx-oauth (>=0.15.0)
Requires-Dist: itsdangerous (>=2.0.0)
Requires-Dist: mcp (>=1.0.0)
Requires-Dist: motor (>=3.0.0) ; extra == "mongodb"
Requires-Dist: mysqlclient (>=2.2.0) ; extra == "mysql"
Requires-Dist: opentelemetry-exporter-otlp (>=1.20.0)
Requires-Dist: opentelemetry-instrumentation-fastapi (>=0.41b0)
Requires-Dist: opentelemetry-instrumentation-httpx (>=0.41b0)
Requires-Dist: opentelemetry-instrumentation-requests (>=0.41b0)
Requires-Dist: opentelemetry-instrumentation-sqlalchemy (>=0.41b0)
Requires-Dist: opentelemetry-propagator-b3 (>=1.20.0)
Requires-Dist: opentelemetry-sdk (>=1.20.0)
Requires-Dist: passlib[bcrypt] (>=1.7.4)
Requires-Dist: prometheus-client (>=0.18.0) ; extra == "metrics"
Requires-Dist: psycopg2-binary (>=2.9.0) ; extra == "pg2"
Requires-Dist: psycopg[binary] (>=3.0) ; extra == "pg"
Requires-Dist: pydantic-settings (>=2.0)
Requires-Dist: pymysql (>=1.1.0) ; extra == "mysql"
Requires-Dist: pyodbc (>=5.0.0) ; extra == "mssql"
Requires-Dist: pyotp (>=2.9.0)
Requires-Dist: python-dotenv (>=1.0.0)
Requires-Dist: redis (>=5.0.0)
Requires-Dist: redshift-connector (>=2.0.0) ; extra == "redshift"
Requires-Dist: snowflake-connector-python (>=3.0.0) ; extra == "snowflake"
Requires-Dist: sqlalchemy[asyncio] (>=2.0)
Requires-Dist: stripe (>=7.0.0) ; extra == "payments" or extra == "stripe"
Requires-Dist: typer (>=0.12.0)
Requires-Dist: websockets (>=12.0)
Project-URL: Documentation, https://nfrax.com/svc-infra
Project-URL: Homepage, https://github.com/nfraxlab/svc-infra
Project-URL: Issues, https://github.com/nfraxlab/svc-infra/issues
Project-URL: Repository, https://github.com/nfraxlab/svc-infra
